pydita_ast/__init__.py
pydita_ast/ast_tree.py
pydita_ast/custom_functions.py
pydita_ast/directory_format.py
pydita_ast/load_xml_doc.py
pydita_ast/version_variables.py
pydita_ast/writer.py
pydita_ast-0.1.0.dist-info/LICENSE
pydita_ast-0.1.0.dist-info/WHEEL
pydita_ast-0.1.0.dist-info/METADATA
pydita_ast-0.1.0.dist-info/RECORD
